orabote_biz/__init__.py
orabote_biz/orabote_biz.py
orabote_biz-0.1.4.dist-info/LICENSE
orabote_biz-0.1.4.dist-info/METADATA
orabote_biz-0.1.4.dist-info/WHEEL
orabote_biz-0.1.4.dist-info/top_level.txt
orabote_biz-0.1.4.dist-info/RECORD
